tinypipe/__init__.py
tinypipe/pipeline.py
tinypipe/blocks/__init__.py
tinypipe/blocks/base_block.py
tinypipe/blocks/pipe/__init__.py
tinypipe/blocks/pipe/base.py
tinypipe/blocks/pipe/batch.py
tinypipe/blocks/pipe/chained.py
tinypipe/blocks/pipe/flat_map.py
tinypipe/blocks/pipe/function.py
tinypipe/blocks/pipe/parallel.py
tinypipe/utils/__init__.py
tinypipe/utils/general.py
tinypipe-0.1.2.dist-info/METADATA
tinypipe-0.1.2.dist-info/RECORD
tinypipe-0.1.2.dist-info/WHEEL
tinypipe-0.1.2.dist-info/top_level.txt
