Metadata-Version: 2.1
Name: tinypipe
Version: 0.1.2
Summary: Lightweight pipeline with multi-threaded operation units.
Home-page: https://github.com/dave-msk/tinypipe
Author: Siu-Kei Muk (David)
Author-email: muksiukei@gmail.com
License: Apache License 2.0
Download-URL: https://github.com/dave-msk/tinypipe/archive/v0.1.2.tar.gz
Keywords: tinypipe,pipeline,multithread
Platform: UNKNOWN
